HanziNLP/__init__.py
HanziNLP/basic.py
HanziNLP/fonts/LiuJianMaoCao-Regular.ttf
HanziNLP/fonts/LongCang-Regular.ttf
HanziNLP/fonts/MaShanZheng-Regular.ttf
HanziNLP/fonts/NotoSerifSC-Black.otf
HanziNLP/fonts/NotoSerifSC-Bold.otf
HanziNLP/fonts/NotoSerifSC-ExtraLight.otf
HanziNLP/fonts/NotoSerifSC-Light.otf
HanziNLP/fonts/NotoSerifSC-Medium.otf
HanziNLP/fonts/NotoSerifSC-Regular.otf
HanziNLP/fonts/NotoSerifSC-SemiBold.otf
HanziNLP/fonts/ZCOOLKuaiLe-Regular.ttf
HanziNLP/stopwords/baidu_stopwords.txt
HanziNLP/stopwords/cn_stopwords.txt
HanziNLP/stopwords/common_stopwords.txt
HanziNLP/stopwords/hit_stopwords.txt
HanziNLP/stopwords/scu_stopwords.txt
HanziNLP-0.1.0.dist-info/LICENSE
HanziNLP-0.1.0.dist-info/METADATA
HanziNLP-0.1.0.dist-info/WHEEL
HanziNLP-0.1.0.dist-info/top_level.txt
HanziNLP-0.1.0.dist-info/RECORD
