Metadata-Version: 2.1
Name: HanziNLP
Version: 0.1.0
Summary: A NLP package specifically for Chinese
Home-page: https://github.com/samzshi0529/HanziNLP
Author: Zhan Shi
Author-email: samzshi@sina.com
License: MIT
Keywords: nlp,chinese,natural language processing,text analysis
Platform: UNKNOWN
License-File: LICENSE
Requires-Dist: jieba (>=0.42.1)
Requires-Dist: matplotlib (>=3.4.3)
Requires-Dist: scikit-learn (>=1.0)
Requires-Dist: pandas
Requires-Dist: numpy
Requires-Dist: gensim
Requires-Dist: fasttext
Requires-Dist: transformers
Requires-Dist: torch
Requires-Dist: ipywidgets (>=7.6.3)
Requires-Dist: IPython (>=7.27.0)
Requires-Dist: seaborn
Requires-Dist: plotly
